{"skeleton":{"hash":"aADw/pLOPSWsW+dPTVYpciXn8gI","spine":"3.4.00","width":246,"height":140},"bones":[{"name":"root"},{"name":"bone","parent":"root","length":51.38,"rotation":270,"x":0.06,"y":54.39},{"name":"bone2","parent":"root","length":24.88,"rotation":-78.43,"x":1.85,"y":56.04},{"name":"bone3","parent":"root","length":37.98,"rotation":90,"x":-0.9,"y":23.77},{"name":"bone5","parent":"root","length":24.88,"rotation":-78.43,"x":-84.21,"y":53.72,"scaleX":0.394,"scaleY":0.394}],"slots":[{"name":"niu1xing2","bone":"bone2","attachment":"niu1xing"},{"name":"niu1xing4","bone":"bone5","attachment":"niu1xing","blend":"additive"},{"name":"niu1guang2","bone":"bone3","attachment":"niu1guang","blend":"additive"},{"name":"niu10","bone":"bone","attachment":"niu4"}],"skins":{"default":{"niu10":{"niu4":{"x":39.4,"y":-11.62,"rotation":89.99,"width":184,"height":140}},"niu1guang2":{"niu1guang":{"x":0.92,"y":-3.34,"rotation":-90,"width":246,"height":48}},"niu1xing2":{"niu1xing":{"x":1.94,"y":-0.88,"rotation":78.43,"width":51,"height":49}},"niu1xing4":{"niu1xing":{"x":1.94,"y":-0.88,"rotation":78.43,"width":51,"height":49}}}},"animations":{"animation":{"slots":{"niu10":{"color":[{"time":0,"color":"ffffff00"},{"time":0.3333,"color":"ffffffff"}]},"niu1guang2":{"color":[{"time":0,"color":"ffffff00"},{"time":0.3333,"color":"ffffffff"}]},"niu1xing2":{"color":[{"time":0,"color":"ffffff00"},{"time":0.3333,"color":"ffffffff","curve":"stepped"},{"time":0.5,"color":"ffffffff","curve":"stepped"},{"time":0.6666,"color":"ffffffff"}]},"niu1xing4":{"color":[{"time":0,"color":"ffffff00","curve":"stepped"},{"time":0.3666,"color":"ffffff00","curve":"stepped"},{"time":0.4,"color":"ffffffff","curve":"stepped"},{"time":0.6666,"color":"ffffffff"},{"time":0.8333,"color":"ffffff00"}],"attachment":[{"time":0,"name":null},{"time":0.4,"name":"niu1xing"}]}},"bones":{"bone3":{"rotate":[{"time":0,"angle":0,"curve":"stepped"},{"time":0.3333,"angle":0,"curve":"stepped"},{"time":0.6666,"angle":0,"curve":"stepped"},{"time":1,"angle":0}],"translate":[{"time":0,"x":-134.88,"y":0},{"time":0.3333,"x":32.87,"y":0},{"time":0.6666,"x":0,"y":0,"curve":"stepped"},{"time":1,"x":0,"y":0}],"scale":[{"time":0,"x":1,"y":0.664},{"time":0.3333,"x":1,"y":1.365},{"time":0.6666,"x":1,"y":1,"curve":"stepped"},{"time":1,"x":1,"y":1}],"shear":[{"time":0,"x":0,"y":0,"curve":"stepped"},{"time":0.3333,"x":0,"y":0,"curve":"stepped"},{"time":0.6666,"x":0,"y":0,"curve":"stepped"},{"time":1,"x":0,"y":0}]},"bone":{"rotate":[{"time":0,"angle":0,"curve":"stepped"},{"time":0.3333,"angle":0,"curve":"stepped"},{"time":0.6666,"angle":0}],"translate":[{"time":0,"x":-80.59,"y":-8.35},{"time":0.3333,"x":18.05,"y":0.9},{"time":0.6666,"x":0,"y":0}],"scale":[{"time":0,"x":1,"y":1,"curve":"stepped"},{"time":0.3333,"x":1,"y":1,"curve":"stepped"},{"time":0.6666,"x":1,"y":1}],"shear":[{"time":0,"x":31.78,"y":0},{"time":0.3333,"x":0,"y":0,"curve":"stepped"},{"time":0.6666,"x":0,"y":0}]},"bone2":{"rotate":[{"time":0,"angle":104.3},{"time":0.3333,"angle":0,"curve":"stepped"},{"time":0.5,"angle":0,"curve":"stepped"},{"time":0.6666,"angle":0}],"translate":[{"time":0,"x":-82.08,"y":-6.31},{"time":0.3333,"x":0,"y":0,"curve":"stepped"},{"time":0.5,"x":0,"y":0,"curve":"stepped"},{"time":0.6666,"x":0,"y":0}],"scale":[{"time":0,"x":1,"y":1},{"time":0.3333,"x":1.568,"y":1.568},{"time":0.5,"x":1,"y":1},{"time":0.5333,"x":0.79,"y":0.79},{"time":0.6,"x":1.256,"y":1.256},{"time":0.6666,"x":1,"y":1}],"shear":[{"time":0,"x":0,"y":0,"curve":"stepped"},{"time":0.3333,"x":0,"y":0,"curve":"stepped"},{"time":0.5,"x":0,"y":0,"curve":"stepped"},{"time":0.6666,"x":0,"y":0}]},"root":{"rotate":[{"time":0,"angle":0}],"translate":[{"time":0,"x":0,"y":0}],"scale":[{"time":0,"x":1,"y":1}],"shear":[{"time":0,"x":0,"y":0}]},"bone5":{"rotate":[{"time":0,"angle":0,"curve":"stepped"},{"time":0.3666,"angle":0,"curve":"stepped"},{"time":0.4,"angle":0,"curve":"stepped"},{"time":0.6666,"angle":0}],"translate":[{"time":0,"x":0,"y":0,"curve":"stepped"},{"time":0.3666,"x":0,"y":0,"curve":"stepped"},{"time":0.4,"x":87.08,"y":4.09},{"time":0.6666,"x":84.65,"y":2.14}],"scale":[{"time":0,"x":1,"y":1,"curve":"stepped"},{"time":0.3666,"x":1,"y":1,"curve":"stepped"},{"time":0.4,"x":2.411,"y":2.411},{"time":0.6666,"x":3.741,"y":3.741},{"time":0.8333,"x":4.865,"y":4.865}],"shear":[{"time":0,"x":0,"y":0,"curve":"stepped"},{"time":0.3666,"x":0,"y":0,"curve":"stepped"},{"time":0.4,"x":0,"y":0,"curve":"stepped"},{"time":0.6666,"x":0,"y":0}]}}}}}